newsub/__init__.py
newsub/main.py
newsub-0.3.3.dist-info/LICENSE
newsub-0.3.3.dist-info/METADATA
newsub-0.3.3.dist-info/WHEEL
newsub-0.3.3.dist-info/entry_points.txt
newsub-0.3.3.dist-info/top_level.txt
newsub-0.3.3.dist-info/RECORD
