Metadata-Version: 2.1
Name: newsub
Version: 0.3.3
Summary: expdite the creation of Slurm submission scripts
Home-page: https://github.com/ghbhc/newsub
Author: ghbhc
Author-email: ghbhc01@gmail.com
License: UNKNOWN
Platform: UNKNOWN
Requires-Python: >=3.6
